[-----------------------------Magic, Minor, Major-----------------------------]
Magic number: 0xcafebabe
Minor Version: 0
Major Version: 46 (Java 1.2)


[--------------------------------Constant Pool--------------------------------]
Constant Pool Count: 30
[1] MethodRef:
    Class: java/lang/Object    *CP Index: 9
    Name And Type: <init> <()V>    *CP Index: 18

[2] Double:
    Double: 4.63661e+18

[3]: 0 (tag unknown)

[4] Double:
    Double: 4.63895e+18

[5]: 0 (tag unknown)

[6] FieldRef:
    Class: java/lang/System    *CP Index: 19
    Name And Type: out <Ljava/io/PrintStream;>    *CP Index: 20

[7] MethodRef:
    Class: java/io/PrintStream    *CP Index: 21
    Name And Type: println <(D)V>    *CP Index: 22

[8] Class:
    Name: double_aritmetica    *CP Index: 23

[9] Class:
    Name: java/lang/Object    *CP Index: 24

[10] UTF8:
    Length: 6
    Content: <init>

[11] UTF8:
    Length: 3
    Content: ()V

[12] UTF8:
    Length: 4
    Content: Code

[13] UTF8:
    Length: 15
    Content: LineNumberTable

[14] UTF8:
    Length: 4
    Content: main

[15] UTF8:
    Length: 22
    Content: ([Ljava/lang/String;)V

[16] UTF8:
    Length: 10
    Content: SourceFile

[17] UTF8:
    Length: 22
    Content: double_aritmetica.java

[18] Name and Type:
    Name: <init>    *CP Index: 10
    Type: ()V    *CP Index: 11

[19] Class:
    Name: java/lang/System    *CP Index: 25

[20] Name and Type:
    Name: out    *CP Index: 26
    Type: Ljava/io/PrintStream;    *CP Index: 27

[21] Class:
    Name: java/io/PrintStream    *CP Index: 28

[22] Name and Type:
    Name: println    *CP Index: 29
    Type: (D)V    *CP Index: 30

[23] UTF8:
    Length: 17
    Content: double_aritmetica

[24] UTF8:
    Length: 16
    Content: java/lang/Object

[25] UTF8:
    Length: 16
    Content: java/lang/System

[26] UTF8:
    Length: 3
    Content: out

[27] UTF8:
    Length: 21
    Content: Ljava/io/PrintStream;

[28] UTF8:
    Length: 19
    Content: java/io/PrintStream

[29] UTF8:
    Length: 7
    Content: println

[30] UTF8:
    Length: 4
    Content: (D)V



[-----------------------------Access, This, Super-----------------------------]
Access Flags: 0x0021 (public)
This Class: double_aritmetica    *CP Index: 8
Super Class: java/lang/Object    *CP Index: 9


[---------------------------------Interfaces----------------------------------]
Interfaces Count: 0


[-----------------------------------Fields------------------------------------]
Fields Count: 0


[-----------------------------------Methods-----------------------------------]
<init> ()V
Access Flags: public (0x01)
Attributes: 
  Code
  Attribute Length: 29
  Code Length: 5
  Bytecode:
    0    aload_0        
    1    invokespecial    #1    java/lang/Object.<init>
    4    return         
  Attributes Count: 1
    cp_index #13 LineNumberTable
    Start PC: 0      Line Number: 6


main ([Ljava/lang/String;)V
Access Flags: public static (0x09)
Attributes: 
  Code
  Attribute Length: 118
  Code Length: 62
  Bytecode:
    0    ldc2_w           #2    1
    3    dstore_1       
    4    ldc2_w           #4    1
    7    dstore_3       
    8    getstatic        #6    java/lang/System.out
    11   dload_1        
    12   dload_3        
    13   dadd           
    14   invokevirtual    #7    java/io/PrintStream.println
    17   getstatic        #6    java/lang/System.out
    20   dload_1        
    21   dload_3        
    22   dsub           
    23   invokevirtual    #7    java/io/PrintStream.println
    26   getstatic        #6    java/lang/System.out
    29   dload_1        
    30   dload_3        
    31   dmul           
    32   invokevirtual    #7    java/io/PrintStream.println
    35   getstatic        #6    java/lang/System.out
    38   dload_1        
    39   dload_3        
    40   ddiv           
    41   invokevirtual    #7    java/io/PrintStream.println
    44   getstatic        #6    java/lang/System.out
    47   dload_1        
    48   dneg           
    49   invokevirtual    #7    java/io/PrintStream.println
    52   getstatic        #6    java/lang/System.out
    55   dload_3        
    56   dload_1        
    57   drem           
    58   invokevirtual    #7    java/io/PrintStream.println
    61   return         
  Attributes Count: 1
    cp_index #13 LineNumberTable
    Start PC: 0      Line Number: 8
    Start PC: 4      Line Number: 9
    Start PC: 8      Line Number: 10
    Start PC: 17     Line Number: 11
    Start PC: 26     Line Number: 12
    Start PC: 35     Line Number: 13
    Start PC: 44     Line Number: 14
    Start PC: 52     Line Number: 15
    Start PC: 61     Line Number: 16


[---------------------------------Attributes----------------------------------]
Attributes Count: 1
----------------------------------------
[1] Attribute Name: SourceFile
    Attribute Name Index: 16
    Attribute Length: 2
    SourceFile: double_aritmetica.java    *CP Index: 17
----------------------------------------
